{
  "color-primary-100": "#DBFCF9",
  "color-primary-200": "#B7F9F9",
  "color-primary-300": "#90E9EF",
  "color-primary-400": "#70D0DF",
  "color-primary-500": "#45AECA",
  "color-primary-600": "#328AAD",
  "color-primary-700": "#226991",
  "color-primary-800": "#164C75",
  "color-primary-900": "#0D3660",
  "color-success-100": "#E6FCDE",
  "color-success-200": "#C8FABF",
  "color-success-300": "#A1F09B",
  "color-success-400": "#7EE180",
  "color-success-500": "#55ce63",
  "color-success-600": "#3EB156",
  "color-success-700": "#2A944A",
  "color-success-800": "#1B773F",
  "color-success-900": "#106238",
  "color-info-100": "#E6F4F6",
  "color-info-200": "#CFE8ED",
  "color-info-300": "#A3C1C9",
  "color-info-400": "#708A93",
  "color-info-500": "#34444c",
  "color-info-600": "#263641",
  "color-info-700": "#1A2936",
  "color-info-800": "#101D2C",
  "color-info-900": "#091424",
  "color-warning-100": "#FFF7CD",
  "color-warning-200": "#FFED9B",
  "color-warning-300": "#FFE16A",
  "color-warning-400": "#FFD545",
  "color-warning-500": "#ffc107",
  "color-warning-600": "#DBA005",
  "color-warning-700": "#B78103",
  "color-warning-800": "#936402",
  "color-warning-900": "#7A4F01",
  "color-danger-100": "#FFEDDB",
  "color-danger-200": "#FFD6B8",
  "color-danger-300": "#FFBA95",
  "color-danger-400": "#FF9F7A",
  "color-danger-500": "#FF724F",
  "color-danger-600": "#DB4D39",
  "color-danger-700": "#B72F27",
  "color-danger-800": "#93191C",
  "color-danger-900": "#7A0F19"
}
